dh_tool/__init__.py
dh_tool/es_tool.py
dh_tool/file_tool.py
dh_tool/application/report/__init__.py
dh_tool/application/report/constants.py
dh_tool/application/report/worker.py
dh_tool/common/__init__.py
dh_tool/common/utils.py
dh_tool/dataframe/__init__.py
dh_tool/dataframe/core/base.py
dh_tool/dataframe/core/sheets.py
dh_tool/dataframe/handlers/dataframe_handler.py
dh_tool/dataframe/handlers/excel_handler.py
dh_tool/dataframe/handlers/visualization_handler.py
dh_tool/dataframe/utils/events.py
dh_tool/excel/__init__.py
dh_tool/excel/config.py
dh_tool/excel/dataframe_manager.py
dh_tool/excel/excel_core.py
dh_tool/excel/sheet.py
dh_tool/excel/style.py
dh_tool/excel/utils.py
dh_tool/gpt_tool/__init__.py
dh_tool/gpt_tool/models.py
dh_tool/gpt_tool/core/__init__.py
dh_tool/gpt_tool/core/base.py
dh_tool/gpt_tool/core/config.py
dh_tool/gpt_tool/core/constants.py
dh_tool/gpt_tool/data/model_price.csv
dh_tool/gpt_tool/factories/chat_service_factory.py
dh_tool/gpt_tool/services/async_chat_service.py
dh_tool/gpt_tool/services/batch_service.py
dh_tool/gpt_tool/services/chat_service.py
dh_tool/gpt_tool/utils/async_stream_processor.py
dh_tool/gpt_tool/utils/message_handler.py
dh_tool/gpt_tool/utils/stream_processor.py
dh_tool/llm_tool/__init__.py
dh_tool/llm_tool/data/token_price_by_model.csv
dh_tool/llm_tool/llm/__init__.py
dh_tool/llm_tool/llm/base.py
dh_tool/llm_tool/llm/gemini.py
dh_tool/llm_tool/llm/gpt.py
dh_tool/llm_tool/utils/__init__.py
dh_tool/llm_tool/utils/gpt_response_schema.py
dh_tool/llm_tool/utils/llm_token_pricing.py
dh_tool/llm_tool/utils/response_parser.py
dh_tool/llm_tool/utils/stream_processor.py
dh_tool/log_tool/__init__.py
dh_tool/log_tool/context_managers.py
dh_tool/log_tool/decorators.py
dh_tool/log_tool/log_levels.py
dh_tool/log_tool/logger.py
dh_tool/log_tool/handlers/__init__.py
dh_tool/log_tool/handlers/console_handler.py
dh_tool/log_tool/handlers/file_handler.py
dh_tool-1.0.59.dist-info/METADATA
dh_tool-1.0.59.dist-info/WHEEL
dh_tool-1.0.59.dist-info/top_level.txt
dh_tool-1.0.59.dist-info/RECORD
