Metadata-Version: 2.4
Name: dh-tool
Version: 1.0.59
Summary: A small example package
Author-email: dohyun <doh0106@naver.com>
Project-URL: Homepage, https://github.com/pypa/sampleproject
Project-URL: Issues, https://github.com/pypa/sampleproject/issues
Classifier: Programming Language :: Python :: 3
Classifier: License :: OSI Approved :: MIT License
Classifier: Operating System :: OS Independent
Requires-Python: >=3.8
Requires-Dist: elasticsearch
Requires-Dist: matplotlib
Requires-Dist: numpy
Requires-Dist: openai
Requires-Dist: openpyxl
Requires-Dist: pandas
Requires-Dist: python_box
Requires-Dist: scikit_learn
Requires-Dist: seaborn
Requires-Dist: tqdm
